asteroidsenv/__init__.py
asteroidsenv/Resources/Images/Agent.png
asteroidsenv/Resources/Images/KeyActive.png
asteroidsenv/Resources/Images/KeyInactive.png
asteroidsenv/Resources/Images/KeyShoot.png
asteroidsenv/Resources/Images/KeyShootInactive.png
asteroidsenv/Resources/Images/Spacerock.png
asteroidsenv/Resources/Images/Spacerock16.png
asteroidsenv/Resources/Images/Spacerock32.png
asteroidsenv/env/__init__.py
asteroidsenv/env/asteroids.py
asteroidsenv/env/resourcemanager.py
asteroidsenv/env/spacerock.py
asteroidsenv/env/spaceship.py
asteroidsenv/env/utils.py
asteroidsenv-1.3.0.dist-info/LICENSE
asteroidsenv-1.3.0.dist-info/METADATA
asteroidsenv-1.3.0.dist-info/WHEEL
asteroidsenv-1.3.0.dist-info/top_level.txt
asteroidsenv-1.3.0.dist-info/RECORD
