Metadata-Version: 2.1
Name: asteroidsenv
Version: 1.3.0
Summary: The atari classic asteroids as gymnasium environment
Author-email: Laurenz Levi Spielmann <laurenz-levi.spielmann@tu-dortmund.de>
License: MIT License
Requires-Python: >=3.8
License-File: LICENSE
Requires-Dist: gymnasium >=0.26.0
Requires-Dist: pygame >=2.1.0
Requires-Dist: numpy >=1.19
